LICENSE
README.md
setup.py
n_sam.egg-info/PKG-INFO
n_sam.egg-info/SOURCES.txt
n_sam.egg-info/dependency_links.txt
n_sam.egg-info/top_level.txt
observations/__init__.py
observations/experiments_trajectories_creator.py
sam_learning/__init__.py
sam_learning/numeric_sam.py
sam_learning/sam_learning.py
solvers/__init__.py
solvers/enhsp_solver.py
solvers/metric_ff_solver.py