Metadata-Version: 2.1
Name: n-sam
Version: 1.0.1
Summary: Numeric Safe Action Model Learning algorithm implementation in Python
Author: Argaman Mordoch
Requires-Python: >=3.8
License-File: LICENSE
